percy/__init__.py
percy/cache.py
percy/page_metadata.py
percy/screenshot.py
percy/version.py
percy_playwright-1.0.1.dist-info/licenses/LICENSE
percy_playwright-1.0.1.dist-info/METADATA
percy_playwright-1.0.1.dist-info/WHEEL
percy_playwright-1.0.1.dist-info/top_level.txt
percy_playwright-1.0.1.dist-info/RECORD
