Metadata-Version: 2.4
Name: percy-playwright
Version: 1.0.1
Summary: Python client for visual testing with Percy
Home-page: https://github.com/percy/percy-playwright-python
Author: Perceptual Inc.
Author-email: team@percy.io
License: MIT
Keywords: percy visual testing
Classifier: Development Status :: 5 - Production/Stable
Classifier: Intended Audience :: Developers
Classifier: License :: OSI Approved :: MIT License
Classifier: Natural Language :: English
Classifier: Programming Language :: Python :: 3.6
Classifier: Programming Language :: Python :: 3.7
Classifier: Programming Language :: Python :: 3.8
Classifier: Programming Language :: Python :: 3.9
Requires-Python: >=3.6
License-File: LICENSE
Requires-Dist: playwright>=1.28.0
Requires-Dist: requests==2.*
Dynamic: author
Dynamic: author-email
Dynamic: classifier
Dynamic: description
Dynamic: description-content-type
Dynamic: home-page
Dynamic: keywords
Dynamic: license
Dynamic: license-file
Dynamic: requires-dist
Dynamic: requires-python
Dynamic: summary
